sampleRedis/__init__.py
sampleRedis/ct_cache.py
ct_sample_redis-0.2.2.dist-info/METADATA
ct_sample_redis-0.2.2.dist-info/WHEEL
ct_sample_redis-0.2.2.dist-info/top_level.txt
ct_sample_redis-0.2.2.dist-info/RECORD
